<?xml version="1.0" encoding="UTF-8" standalone="yes"?>
<sst xmlns="http://schemas.openxmlformats.org/spreadsheetml/2006/main" count="448" uniqueCount="448"><si><t>25-21-225-004-0000</t></si><si><t>25-21-221-022-0000</t></si><si><t>25-21-220-026-0000</t></si><si><t>25-21-218-007-0000</t></si><si><t>25-21-215-004-0000</t></si><si><t>25-21-208-022-0000</t></si><si><t>25-21-208-020-0000</t></si><si><t>25-21-206-014-0000</t></si><si><t>25-21-129-020-0000</t></si><si><t>25-21-119-003-0000</t></si><si><t>25-21-115-032-0000</t></si><si><t>25-21-104-012-0000</t></si><si><t>25-20-424-070-0000</t></si><si><t>25-20-421-006-0000</t></si><si><t>25-20-417-017-0000</t></si><si><t>25-20-416-036-0000</t></si><si><t>25-20-328-122-0000</t></si><si><t>25-20-310-023-0000</t></si><si><t>25-20-216-020-0000</t></si><si><t>25-20-132-014-0000</t></si><si><t>25-20-123-055-0000</t></si><si><t>25-20-123-053-0000</t></si><si><t>25-20-122-067-0000</t></si><si><t>25-20-108-015-0000</t></si><si><t>25-20-103-012-0000</t></si><si><t>25-19-204-015-0000</t></si><si><t>25-17-422-017-0000</t></si><si><t>25-17-412-033-0000</t></si><si><t>25-17-412-007-0000</t></si><si><t>25-17-333-006-0000</t></si><si><t>25-17-333-005-0000</t></si><si><t>25-17-320-026-0000</t></si><si><t>25-17-312-036-0000</t></si><si><t>25-17-312-015-0000</t></si><si><t>25-17-224-004-0000</t></si><si><t>25-17-216-021-0000</t></si><si><t>25-17-216-015-0000</t></si><si><t>25-17-210-013-0000</t></si><si><t>25-16-427-022-0000</t></si><si><t>25-16-426-017-0000</t></si><si><t>25-16-425-032-0000</t></si><si><t>25-16-424-051-0000</t></si><si><t>25-16-423-007-0000</t></si><si><t>25-16-420-029-0000</t></si><si><t>25-16-415-018-0000</t></si><si><t>25-16-412-013-0000</t></si><si><t>25-16-410-030-0000</t></si><si><t>25-16-406-018-0000</t></si><si><t>25-16-405-025-0000</t></si><si><t>25-16-402-019-0000</t></si><si><t>25-16-402-017-0000</t></si><si><t>25-16-217-086-0000</t></si><si><t>25-16-216-057-0000</t></si><si><t>25-16-216-053-0000</t></si><si><t>25-16-215-044-0000</t></si><si><t>25-16-215-025-0000</t></si><si><t>25-16-214-055-0000</t></si><si><t>25-16-214-027-0000</t></si><si><t>25-16-214-002-0000</t></si><si><t>25-16-211-036-0000</t></si><si><t>25-16-210-075-0000</t></si><si><t>25-16-206-106-0000</t></si><si><t>25-16-206-075-0000</t></si><si><t>25-16-206-069-0000</t></si><si><t>25-16-204-020-0000</t></si><si><t>25-16-202-072-0000</t></si><si><t>25-16-202-040-0000</t></si><si><t>25-16-106-002-0000</t></si><si><t>25-09-429-004-0000</t></si><si><t>25-09-423-031-0000</t></si><si><t>25-09-406-027-0000</t></si><si><t>25-09-405-004-0000</t></si><si><t>25-09-330-025-0000</t></si><si><t>25-09-326-012-0000</t></si><si><t>25-09-326-010-0000</t></si><si><t>25-09-303-003-0000</t></si><si><t>25-08-419-012-0000</t></si><si><t>25-08-303-007-0000</t></si><si><t>25-08-110-022-0000</t></si><si><t>25-08-103-021-0000</t></si><si><t>25-06-200-011-0000</t></si><si><t>25-05-217-036-0000</t></si><si><t>25-04-318-063-0000</t></si><si><t>25-04-205-027-0000</t></si><si><t>25-04-111-036-0000</t></si><si><t>20-33-310-021-0000</t></si><si><t>20-33-306-007-0000</t></si><si><t>20-33-110-065-0000</t></si><si><t>20-33-105-029-0000</t></si><si><t>20-33-105-008-0000</t></si><si><t>20-33-102-030-0000</t></si><si><t>20-32-417-031-0000</t></si><si><t>20-32-412-004-0000</t></si><si><t>20-32-410-004-0000</t></si><si><t>20-32-202-033-0000</t></si><si><t>20-32-114-024-0000</t></si><si><t>20-31-212-029-0000</t></si><si><t>20-30-410-016-0000</t></si><si><t>20-30-316-007-0000</t></si><si><t>20-30-221-027-0000</t></si><si><t>20-30-221-023-0000</t></si><si><t>20-30-221-019-0000</t></si><si><t>20-30-219-016-0000</t></si><si><t>20-30-217-014-0000</t></si><si><t>20-30-211-026-0000</t></si><si><t>20-30-209-047-0000</t></si><si><t>20-30-209-031-0000</t></si><si><t>20-30-203-043-0000</t></si><si><t>20-30-203-008-0000</t></si><si><t>20-30-200-006-0000</t></si><si><t>20-30-104-004-0000</t></si><si><t>20-29-427-015-0000</t></si><si><t>20-29-319-018-0000</t></si><si><t>20-29-229-035-0000</t></si><si><t>20-29-225-036-0000</t></si><si><t>20-29-223-015-0000</t></si><si><t>20-29-219-026-0000</t></si><si><t>20-29-219-012-0000</t></si><si><t>20-29-217-003-0000</t></si><si><t>20-29-211-024-0000</t></si><si><t>20-29-203-024-0000</t></si><si><t>20-29-202-038-0000</t></si><si><t>20-29-132-063-0000</t></si><si><t>20-29-125-012-0000</t></si><si><t>20-29-123-021-0000</t></si><si><t>20-29-122-020-0000</t></si><si><t>20-29-117-015-0000</t></si><si><t>20-29-112-022-0000</t></si><si><t>20-29-110-015-0000</t></si><si><t>20-29-104-007-0000</t></si><si><t>20-29-101-020-0000</t></si><si><t>20-28-418-001-0000</t></si><si><t>20-28-400-023-0000</t></si><si><t>20-28-221-011-0000</t></si><si><t>20-28-216-020-0000</t></si><si><t>20-28-213-029-0000</t></si><si><t>20-28-211-011-0000</t></si><si><t>20-28-206-032-0000</t></si><si><t>20-28-202-020-0000</t></si><si><t>20-28-110-023-0000</t></si><si><t>20-21-400-007-0000</t></si><si><t>20-21-326-029-0000</t></si><si><t>20-21-320-016-0000</t></si><si><t>20-21-302-004-0000</t></si><si><t>20-21-217-024-0000</t></si><si><t>20-21-121-027-0000</t></si><si><t>20-21-115-035-0000</t></si><si><t>20-21-112-002-0000</t></si><si><t>PIN NUMBER</t></si><si><t>VOL</t></si><si><t>Cert Number</t></si><si><t>11-0011243</t></si><si><t>11-0011250</t></si><si><t>11-0011253</t></si><si><t>11-0011261</t></si><si><t>11-0011266</t></si><si><t>11-0011281</t></si><si><t>11-0011285</t></si><si><t>11-0011289</t></si><si><t>11-0011305</t></si><si><t>11-0011310</t></si><si><t>11-0011311</t></si><si><t>11-0011313</t></si><si><t>11-0011315</t></si><si><t>11-0011319</t></si><si><t>11-0011323</t></si><si><t>11-0011360</t></si><si><t>11-0011363</t></si><si><t>11-0011367</t></si><si><t>11-0011370</t></si><si><t>11-0011377</t></si><si><t>11-0011380</t></si><si><t>11-0011390</t></si><si><t>11-0011397</t></si><si><t>11-0011398</t></si><si><t>11-0011400</t></si><si><t>11-0011408</t></si><si><t>11-0011412</t></si><si><t>11-0011413</t></si><si><t>11-0011424</t></si><si><t>11-0011435</t></si><si><t>11-0011438</t></si><si><t>11-0011439</t></si><si><t>11-0011445</t></si><si><t>11-0011447</t></si><si><t>11-0011450</t></si><si><t>11-0011458</t></si><si><t>11-0011485</t></si><si><t>11-0011495</t></si><si><t>11-0011508</t></si><si><t>11-0011516</t></si><si><t>11-0011518</t></si><si><t>11-0011528</t></si><si><t>11-0011529</t></si><si><t>11-0011532</t></si><si><t>11-0011539</t></si><si><t>11-0011542</t></si><si><t>11-0011544</t></si><si><t>11-0011545</t></si><si><t>11-0011546</t></si><si><t>11-0011554</t></si><si><t>11-0011560</t></si><si><t>11-0011599</t></si><si><t>11-0011637</t></si><si><t>11-0011665</t></si><si><t>11-0011734</t></si><si><t>11-0011736</t></si><si><t>11-0011742</t></si><si><t>11-0011759</t></si><si><t>11-0011761</t></si><si><t>11-0011762</t></si><si><t>11-0011767</t></si><si><t>11-0011788</t></si><si><t>11-0011792</t></si><si><t>11-0011855</t></si><si><t>11-0011876</t></si><si><t>11-0011889</t></si><si><t>11-0011947</t></si><si><t>11-0011990</t></si><si><t>11-0012035</t></si><si><t>11-0012043</t></si><si><t>11-0012066</t></si><si><t>11-0012080</t></si><si><t>11-0012123</t></si><si><t>11-0012145</t></si><si><t>11-0012146</t></si><si><t>11-0012151</t></si><si><t>11-0012156</t></si><si><t>11-0012158</t></si><si><t>11-0012175</t></si><si><t>11-0012178</t></si><si><t>11-0012186</t></si><si><t>11-0012197</t></si><si><t>11-0012200</t></si><si><t>11-0012202</t></si><si><t>11-0012206</t></si><si><t>11-0012207</t></si><si><t>11-0012209</t></si><si><t>11-0012218</t></si><si><t>11-0012221</t></si><si><t>11-0012225</t></si><si><t>11-0012227</t></si><si><t>11-0012228</t></si><si><t>11-0012231</t></si><si><t>11-0012232</t></si><si><t>11-0012236</t></si><si><t>11-0012237</t></si><si><t>11-0012241</t></si><si><t>11-0012263</t></si><si><t>11-0012264</t></si><si><t>11-0012267</t></si><si><t>11-0012268</t></si><si><t>11-0012274</t></si><si><t>11-0012277</t></si><si><t>11-0012281</t></si><si><t>11-0012286</t></si><si><t>11-0012289</t></si><si><t>11-0012291</t></si><si><t>11-0012293</t></si><si><t>11-0012294</t></si><si><t>11-0012296</t></si><si><t>11-0012307</t></si><si><t>11-0012313</t></si><si><t>11-0012314</t></si><si><t>11-0012320</t></si><si><t>11-0012322</t></si><si><t>11-0012324</t></si><si><t>11-0012328</t></si><si><t>11-0012336</t></si><si><t>11-0012337</t></si><si><t>11-0012344</t></si><si><t>11-0012346</t></si><si><t>11-0012352</t></si><si><t>11-0012381</t></si><si><t>11-0012408</t></si><si><t>11-0012409</t></si><si><t>11-0012415</t></si><si><t>11-0012419</t></si><si><t>11-0012420</t></si><si><t>11-0012428</t></si><si><t>11-0012439</t></si><si><t>11-0012452</t></si><si><t>11-0012464</t></si><si><t>11-0012482</t></si><si><t>11-0012485</t></si><si><t>11-0012487</t></si><si><t>11-0012493</t></si><si><t>11-0012498</t></si><si><t>11-0012504</t></si><si><t>11-0012506</t></si><si><t>11-0012517</t></si><si><t>11-0012526</t></si><si><t>11-0012529</t></si><si><t>11-0012530</t></si><si><t>11-0012538</t></si><si><t>11-0012541</t></si><si><t>11-0012542</t></si><si><t>11-0012544</t></si><si><t>11-0012549</t></si><si><t>Address</t></si><si><t>6405 S. PARNELL AVE, CHICAGO, IL 60621-2719</t></si><si><t>6540 S. EMERALD AVE, CHICAGO, IL 60621-2614</t></si><si><t>6516 S. STEWART AVE, CHICAGO, IL 60621-3110</t></si><si><t>6624 S. PERRY AVE, CHICAGO, IL 60621-3807</t></si><si><t>6949 S. EGGLESTON AVE, CHICAGO, IL 60621-2454</t></si><si><t>7038 S. NORMAL BLVD, CHICAGO, IL 60621-3023</t></si><si><t>341 W. MARQUETTE RD, CHICAGO, IL 60621-3724</t></si><si><t>7210 S. LOWE AVE, CHICAGO, IL 60621-2350</t></si><si><t>7120 S. YALE AVE, CHICAGO, IL 60621-3565</t></si><si><t>7120 S. LAFAYETTE AVE, CHICAGO, IL 60621-3513</t></si><si><t>7251 S. YALE AVE, CHICAGO, IL 60621-3540</t></si><si><t>7218 S. PERRY AVE, CHICAGO, IL 60621-3516</t></si><si><t>7320 S. HARVARD AVE, CHICAGO, IL 60621-3422</t></si><si><t>7337 S. PERRY AVE, CHICAGO, IL 60621-3501</t></si><si><t>7550 S. HARVARD AVE, CHICAGO, IL 60620-1615</t></si><si><t>55 W. 77TH PL, CHICAGO, IL 60620-1013</t></si><si><t>1458 W. 71ST PL, CHICAGO, IL 60636-3962</t></si><si><t>1265 W. 71ST ST, CHICAGO, IL 60636-4157</t></si><si><t>1515 W. 72ND ST, CHICAGO, IL 60636-4023</t></si><si><t>1412 W. 72ND PL, CHICAGO, IL 60636-4004</t></si><si><t>1432 W. 73RD ST, CHICAGO, IL 60636-4006</t></si><si><t>1416 W. 73RD PL, CHICAGO, IL 60636-4010</t></si><si><t>1320 W. 73RD PL, CHICAGO, IL 60636-4141</t></si><si><t>1509 W. 73RD PL, CHICAGO, IL 60636-4011</t></si><si><t>1269 W. 74TH ST, CHICAGO, IL 60636-4103</t></si><si><t>7138 S. CARPENTER ST, CHICAGO, IL 60621-1027</t></si><si><t>7114 S. MORGAN ST, CHICAGO, IL 60621-1041</t></si><si><t>7204 S. MORGAN ST, CHICAGO, IL 60621-1043</t></si><si><t>7307 S. MAY ST, CHICAGO, IL 60621-1036</t></si><si><t>7331 S. CARPENTER ST, CHICAGO, IL 60621-1030</t></si><si><t>7336 S. MORGAN ST, CHICAGO, IL 60621-1045</t></si><si><t>7337 S. GREEN ST, CHICAGO, IL 60621-1613</t></si><si><t>7440 S. ABERDEEN ST, CHICAGO, IL 60621-1025</t></si><si><t>843 W. 74TH ST, CHICAGO, IL 60621-1641</t></si><si><t>7818 S. LOOMIS BLVD, CHICAGO, IL 60620-3752</t></si><si><t>7847 S. CARPENTER ST, CHICAGO, IL 60620-2922</t></si><si><t>2129 W. 71ST ST, CHICAGO, IL 60636-3617</t></si><si><t>1945 W. 71ST ST, CHICAGO, IL 60636-3750</t></si><si><t>1809 W. 71ST ST, CHICAGO, IL 60636-3706</t></si><si><t>7150 S. WOOD ST, CHICAGO, IL 60636-3828</t></si><si><t>7218 S. WOLCOTT AVE, CHICAGO, IL 60636-3740</t></si><si><t>7254 S. WOLCOTT AVE, CHICAGO, IL 60636-3740</t></si><si><t>7202 S. WOOD ST, CHICAGO, IL 60636-3815</t></si><si><t>7333 S. WINCHESTER AVE, CHICAGO, IL 60636-3737</t></si><si><t>7341 S. HONORE ST, CHICAGO, IL 60636-3702</t></si><si><t>7347 S. HERMITAGE AVE, CHICAGO, IL 60636-3846</t></si><si><t>7357 S. HERMITAGE AVE, CHICAGO, IL 60636-3846</t></si><si><t>7306 S. PAULINA ST, CHICAGO, IL 60636-3813</t></si><si><t>7821 S. HOYNE AVE, CHICAGO, IL 60620-5742</t></si><si><t>8036 S. HERMITAGE AVE, CHICAGO, IL 60620-4518</t></si><si><t>8018 S. ELIZABETH ST, CHICAGO, IL 60620-3826</t></si><si><t>7950 S. CARPENTER ST, CHICAGO, IL 60620-3052</t></si><si><t>8409 S. ABERDEEN ST, CHICAGO, IL 60620-3314</t></si><si><t>8411 S. MORGAN ST, CHICAGO, IL 60620-3245</t></si><si><t>8532 S. ABERDEEN ST, CHICAGO, IL 60620-3315</t></si><si><t>7919 S. PARNELL AVE, CHICAGO, IL 60620-1749</t></si><si><t>520 W. 80TH ST, CHICAGO, IL 60620-1726</t></si><si><t>8045 S. UNION AVE, CHICAGO, IL 60620-2522</t></si><si><t>8330 S. KERFOOT AVE, CHICAGO, IL 60620-1930</t></si><si><t>8449 S. GILBERT CT, CHICAGO, IL 60620-1919</t></si><si><t>8842 S. WALLACE ST, CHICAGO, IL 60620-2132</t></si><si><t>8836 S. PRINCETON AVE, CHICAGO, IL 60620-1324</t></si><si><t>9345 S. UNION AVE, CHICAGO, IL 60620-2340</t></si><si><t>1148 W. 90TH ST, CHICAGO, IL 60620-3526</t></si><si><t>1929 W. 87TH ST, CHICAGO, IL 60620-6051</t></si><si><t>9603 S. BISHOP ST, CHICAGO, IL 60643-1311</t></si><si><t>1344 W. 97TH PL, CHICAGO, IL 60643-1422</t></si><si><t>9941 S. WINSTON AVE, CHICAGO, IL 60643-1325</t></si><si><t>10133 S. CARPENTER ST, CHICAGO, IL 60643-2214</t></si><si><t>9907 S. LOWE AVE, CHICAGO, IL 60628-1039</t></si><si><t>10231 S. UNION AVE, CHICAGO, IL 60628-1828</t></si><si><t>10239 S. UNION AVE, CHICAGO, IL 60628-1828</t></si><si><t>10224 S. EGGLESTON AVE, CHICAGO, IL 60628-1960</t></si><si><t>9911 S. LASALLE ST, CHICAGO, IL 60628-1311</t></si><si><t>9914 S. LAFAYETTE AVE, CHICAGO, IL 60628-1340</t></si><si><t>10150 S. STATE ST, CHICAGO, IL 60628-2031</t></si><si><t>10211 S. PERRY AVE, CHICAGO, IL 60628-2038</t></si><si><t>10337 S. WALLACE ST, CHICAGO, IL 60628-2453</t></si><si><t>150 W. 103RD PL, CHICAGO, IL 60628-2612</t></si><si><t>14 W. 103RD PL, CHICAGO, IL 60628-2610</t></si><si><t>111 W. 103RD PL, CHICAGO, IL 60628-2611</t></si><si><t>327 W. 104TH PL, CHICAGO, IL 60628-2515</t></si><si><t>309 W. 104TH PL, CHICAGO, IL 60628-2515</t></si><si><t>304 W. 105TH ST, CHICAGO, IL 60628-2520</t></si><si><t>10510 S. WENTWORTH AVE, CHICAGO, IL 60628-2540</t></si><si><t>328 W. 106TH ST, CHICAGO, IL 60628-2534</t></si><si><t>10505 S. LASALLE ST, CHICAGO, IL 60628-2601</t></si><si><t>10617 S. LASALLE ST, CHICAGO, IL 60628-2603</t></si><si><t>10618 S. PERRY AVE, CHICAGO, IL 60628-2635</t></si><si><t>10615 S. PERRY AVE, CHICAGO, IL 60628-2634</t></si><si><t>10546 S. LAFAYETTE AVE, CHICAGO, IL 60628-2629</t></si><si><t>10602 S. STATE ST, CHICAGO, IL 60628-2641</t></si><si><t>10618 S. STATE ST, CHICAGO, IL 60628-2641</t></si><si><t>246 W. 107TH ST, CHICAGO, IL 60628-3302</t></si><si><t>254 W. 108TH ST, CHICAGO, IL 60628-3334</t></si><si><t>248 W. 108TH ST, CHICAGO, IL 60628-3334</t></si><si><t>10722 S. LAFAYETTE AVE, CHICAGO, IL 60628-3427</t></si><si><t>10708 S. STATE ST, CHICAGO, IL 60628-3402</t></si><si><t>10804 S. STATE ST, CHICAGO, IL 60628-3410</t></si><si><t>221 W. 108TH PL, CHICAGO, IL 60628-3321</t></si><si><t>305 W. 109TH ST, CHICAGO, IL 60628-3309</t></si><si><t>236 W. 110TH ST, CHICAGO, IL 60628-4229</t></si><si><t>339 W. 110TH ST, CHICAGO, IL 60628-4148</t></si><si><t>239 W. 110TH PL, CHICAGO, IL 60628-4212</t></si><si><t>118 W. 110TH PL, CHICAGO, IL 60628-4211</t></si><si><t>54 W. 110TH PL, CHICAGO, IL 60628-4231</t></si><si><t>328 W. 111TH ST, CHICAGO, IL 60628-4125</t></si><si><t>1107 W. 104TH PL, CHICAGO, IL 60643-3004</t></si><si><t>10506 S. MAY ST, CHICAGO, IL 60643-3037</t></si><si><t>10534 S. MAY ST, CHICAGO, IL 60643-3037</t></si><si><t>1119 W. 106TH ST, CHICAGO, IL 60643-3054</t></si><si><t>1317 W. 108TH ST, CHICAGO, IL 60643-3601</t></si><si><t>1316 W. 108TH PL, CHICAGO, IL 60643-3603</t></si><si><t>1242 W. 109TH PL, CHICAGO, IL 60643-3707</t></si><si><t>1347 W. 110TH PL, CHICAGO, IL 60643-3615</t></si><si><t>1345 W. 110TH PL, CHICAGO, IL 60643-3615</t></si><si><t>1143 W. 110TH ST, CHICAGO, IL 60643-3743</t></si><si><t>1126 W. 110TH PL, CHICAGO, IL 60643-3711</t></si><si><t>842 W. 111TH ST, CHICAGO, IL 60643-3839</t></si><si><t>11141 S. ASHLAND AVE, CHICAGO, IL 60643-3513</t></si><si><t>1331 W. 111TH ST, CHICAGO, IL 60643-3617</t></si><si><t>1466 W. 112TH PL, CHICAGO, IL 60643-4369</t></si><si><t>11340 S. ADA ST, CHICAGO, IL 60643-4426</t></si><si><t>11341 S. ADA ST, CHICAGO, IL 60643-4425</t></si><si><t>11355 S. ADA ST, CHICAGO, IL 60643-4425</t></si><si><t>1216 W. 115TH ST, CHICAGO, IL 60643-4422</t></si><si><t>11319 S. CARPENTER ST, CHICAGO, IL 60643-4626</t></si><si><t>11606 S. LAFLIN ST, CHICAGO, IL 60643-5032</t></si><si><t>11524 S. RACINE AVE, CHICAGO, IL 60643-5135</t></si><si><t>11734 S. SANGAMON ST, CHICAGO, IL 60643-5234</t></si><si><t>11745 S. SANGAMON ST, CHICAGO, IL 60643-5233</t></si><si><t>11817 S. SANGAMON ST, CHICAGO, IL 60643-5235</t></si><si><t>11549 S. SANGAMON ST, CHICAGO, IL 60643-5268</t></si><si><t>11135 S. WALLACE ST, CHICAGO, IL 60628-4013</t></si><si><t>11246 S. STEWART AVE, CHICAGO, IL 60628-4750</t></si><si><t>11436 S. NORMAL AVE, CHICAGO, IL 60628-4742</t></si><si><t>146 W. 112TH ST, CHICAGO, IL 60628-4804</t></si><si><t>320 W. 112TH PL, CHICAGO, IL 60628-4135</t></si><si><t>316 W. 112TH PL, CHICAGO, IL 60628-4135</t></si><si><t>59 W. 112TH PL, CHICAGO, IL 60628-4805</t></si><si><t>235 W. 113TH ST, CHICAGO, IL 60628-4163</t></si><si><t>108 W. 113TH PL, CHICAGO, IL 60628-4813</t></si><si><t>42 W. 113TH PL, CHICAGO, IL 60628-4811</t></si><si><t>315 W. 114TH ST, CHICAGO, IL 60628-4107</t></si><si><t>633 W. MARQUEETTE RD, CHICAGO, IL 60621</t></si><si><t>7551 S. PAULINA ST, CHICAGO, IL 60620</t></si><si><t>7626 S. LOWE AVE, CHICAGO, IL 60620</t></si><si><t>11309 S. LOWE AVE, CHICAGO, IL 60628</t></si></sst>